MISA_XGModel/MISAFunctions.py
MISA_XGModel/MISA_model.py
MISA_XGModel/__init__.py
MISA_XGModel-0.2.5.dist-info/METADATA
MISA_XGModel-0.2.5.dist-info/WHEEL
MISA_XGModel-0.2.5.dist-info/top_level.txt
MISA_XGModel-0.2.5.dist-info/RECORD
