Metadata-Version: 2.1
Name: MISA_XGModel
Version: 0.2.5
Summary: A Python library for predicting electron density using XGBoost
Home-page: https://github.com/mcardonaserrano/MISA_XGModel
Author: Mateo Cardona Serrano
Author-email: mcardonaserrano@berkeley.edu
Classifier: Programming Language :: Python :: 3
Classifier: License :: OSI Approved :: MIT License
Classifier: Operating System :: OS Independent
Requires-Python: >=3.7
Requires-Dist: xgboost
Requires-Dist: numpy
Requires-Dist: xarray
Requires-Dist: scikit-learn
Requires-Dist: netcdf4
Requires-Dist: pandas
Requires-Dist: tqdm
Requires-Dist: netCDF4
